autofaq_api/__init__.py
autofaq_api/crud.py
autofaq_api/external.py
autofaq_api/http_client.py
autofaq_api/kb_query.py
autofaq_api-0.0.2.dist-info/METADATA
autofaq_api-0.0.2.dist-info/WHEEL
autofaq_api-0.0.2.dist-info/top_level.txt
autofaq_api-0.0.2.dist-info/RECORD
