Metadata-Version: 2.1
Name: autofaq-api
Version: 0.0.2
Summary: Этот модуль умеет работать с 3-мя API AutoFaq: External API, CRUD API, QUERY API. Как синхронно так и асинхронно
Home-page: https://github.com/azatkhafizov/autofaq-api
Author: AzatXafizof
Author-email: hafizov.azat.m@gmail.com
Project-URL: GitHub, https://github.com/azatkhafizov/autofaq-api
Keywords: AutoFaq AutoFAQ autofaq kb
Classifier: Programming Language :: Python :: 3.11
Classifier: License :: OSI Approved :: MIT License
Classifier: Operating System :: OS Independent
Requires-Python: >=3.10
Requires-Dist: aiohttp>=2.25.1
Requires-Dist: aiohttp>=3.12.13
Requires-Dist: aiofiles==24.1.0
Requires-Dist: requests-toolbelt==1.0.0
Requires-Dist: pydantic>=2.9.2
